vynus/__init__.py
vynus/base.py
vynus-0.0.1.dist-info/METADATA
vynus-0.0.1.dist-info/WHEEL
vynus-0.0.1.dist-info/top_level.txt
vynus-0.0.1.dist-info/RECORD
